baloon/__init__.py
baloon/__main__.py
baloon/cli.py
baloon/core.py
baloon/exceptions.py
baloon/formats.py
baloon-1.0.1.dist-info/METADATA
baloon-1.0.1.dist-info/WHEEL
baloon-1.0.1.dist-info/entry_points.txt
baloon-1.0.1.dist-info/licenses/LICENSE
baloon-1.0.1.dist-info/RECORD
