Metadata-Version: 2.4
Name: baloon
Version: 1.0.1
Summary: Baloon: Modern geospatial vector format interconverter and CLI toolkit.
Author: Eric Miguel Ribeiro
License: # GNU GENERAL PUBLIC LICENSE
License-File: LICENSE
Keywords: baloon,bln,cli,converter,geojson,geospatial,gis,interconversion,shapefile,svg
Classifier: Environment :: Console
Classifier: Intended Audience :: Science/Research
Classifier: License :: OSI Approved :: GNU General Public License v3 or later (GPLv3+)
Classifier: Operating System :: OS Independent
Classifier: Programming Language :: Python :: 3
Classifier: Topic :: Scientific/Engineering :: GIS
Requires-Python: >=3.10
Requires-Dist: fastkml>=1.1.0
Requires-Dist: fiona>=1.9
Requires-Dist: geopandas>=0.14
Requires-Dist: lxml>=5.0.0
Requires-Dist: pandas>=2.2
Requires-Dist: pygeoif>=1.5.1
Requires-Dist: pyproj>=3.6
Requires-Dist: rich>=13.7
Requires-Dist: shapely>=2.0
Requires-Dist: typer>=0.12
Provides-Extra: dev
Requires-Dist: pyright>=1.1.370; extra == 'dev'
Requires-Dist: pytest-cov>=5.0; extra == 'dev'
Requires-Dist: pytest>=8.0; extra == 'dev'
Requires-Dist: ruff>=0.5.0; extra == 'dev'
Requires-Dist: types-geopandas>=1.1.1.20250809; extra == 'dev'
Requires-Dist: types-python-dateutil; extra == 'dev'
Requires-Dist: types-pytz; extra == 'dev'
Requires-Dist: types-shapely>=2.1.0.20250809; extra == 'dev'
